archeryutils/__init__.py
archeryutils/length.py
archeryutils/load_rounds.py
archeryutils/rounds.py
archeryutils/targets.py
archeryutils/utils.py
archeryutils/classifications/AGB_ages.json
archeryutils/classifications/AGB_bowstyles.json
archeryutils/classifications/AGB_classes_in.json
archeryutils/classifications/AGB_classes_out.json
archeryutils/classifications/AGB_genders.json
archeryutils/classifications/__init__.py
archeryutils/classifications/agb_field_classifications.py
archeryutils/classifications/agb_indoor_classifications.py
archeryutils/classifications/agb_old_field_classifications.py
archeryutils/classifications/agb_old_indoor_classifications.py
archeryutils/classifications/agb_outdoor_classifications.py
archeryutils/classifications/classification_utils.py
archeryutils/classifications/classifications.py
archeryutils/classifications/tests/__init__.py
archeryutils/classifications/tests/test_agb_field.py
archeryutils/classifications/tests/test_agb_indoor.py
archeryutils/classifications/tests/test_agb_old_field.py
archeryutils/classifications/tests/test_agb_old_indoor.py
archeryutils/classifications/tests/test_agb_outdoor.py
archeryutils/classifications/tests/test_classification_utils.py
archeryutils/handicaps/__init__.py
archeryutils/handicaps/handicap_functions.py
archeryutils/handicaps/handicap_scheme.py
archeryutils/handicaps/handicap_scheme_aa.py
archeryutils/handicaps/handicap_scheme_agb.py
archeryutils/handicaps/handicap_tables.py
archeryutils/handicaps/tests/__init__.py
archeryutils/handicaps/tests/test_handicap_tables.py
archeryutils/handicaps/tests/test_handicaps.py
archeryutils/round_data_files/AGB_VI.json
archeryutils/round_data_files/AGB_indoor.json
archeryutils/round_data_files/AGB_outdoor_imperial.json
archeryutils/round_data_files/AGB_outdoor_metric.json
archeryutils/round_data_files/IFAA_field.json
archeryutils/round_data_files/Miscellaneous.json
archeryutils/round_data_files/WA_VI.json
archeryutils/round_data_files/WA_field.json
archeryutils-1.1.1.dist-info/LICENSE
archeryutils-1.1.1.dist-info/METADATA
archeryutils-1.1.1.dist-info/WHEEL
archeryutils-1.1.1.dist-info/top_level.txt
archeryutils-1.1.1.dist-info/RECORD
