Metadata-Version: 2.1
Name: archeryutils
Version: 1.1.1
Summary: A collection of archery utilities in python.
Author-email: Jack Atkinson <jack.atkinson1000@gmail.com>
License: MIT License
Project-URL: Homepage, https://github.com/jatkinson1000/archeryutils
Project-URL: Bug Tracker, https://github.com/jatkinson1000/archeryutils/issues
Project-URL: Documentation, https://archeryutils.readthedocs.io/
Project-URL: Repository, https://github.com/jatkinson1000/archeryutils
Classifier: License :: OSI Approved :: MIT License
Classifier: Development Status :: 5 - Production/Stable
Classifier: Natural Language :: English
Classifier: Programming Language :: Python
Classifier: Programming Language :: Python :: 3 :: Only
Classifier: Programming Language :: Python :: 3.10
Classifier: Programming Language :: Python :: 3.11
Classifier: Programming Language :: Python :: 3.12
Classifier: Programming Language :: Python :: 3.13
Classifier: Typing :: Typed
Classifier: Operating System :: OS Independent
Requires-Python: >=3.10
License-File: LICENSE
Requires-Dist: numpy>=1.20.0
Provides-Extra: test
Requires-Dist: pytest>=7.2.0; extra == "test"
Requires-Dist: pytest-mock; extra == "test"
Provides-Extra: lint
Requires-Dist: mypy>=1.0.0; extra == "lint"
Requires-Dist: coverage; extra == "lint"
Requires-Dist: pytest>=7.2.0; extra == "lint"
Requires-Dist: pytest-mock; extra == "lint"
Requires-Dist: ruff>=0.7.3; extra == "lint"
Requires-Dist: blackdoc; extra == "lint"
Provides-Extra: docs
Requires-Dist: sphinx; extra == "docs"
Requires-Dist: sphinx_rtd_theme; extra == "docs"
Requires-Dist: sphinx-toolbox; extra == "docs"
Requires-Dist: nbsphinx; extra == "docs"
Requires-Dist: ipython; extra == "docs"
Requires-Dist: pickleshare; extra == "docs"
Requires-Dist: ruff>=0.7.3; extra == "docs"
Requires-Dist: blackdoc; extra == "docs"
